fancylogger/__init__.py
fancylogger/decorators.py
fancylogger/utils/__init__.py
fancylogger/utils/timer.py
fancylogger_demo-0.1.1.dist-info/METADATA
fancylogger_demo-0.1.1.dist-info/WHEEL
fancylogger_demo-0.1.1.dist-info/top_level.txt
fancylogger_demo-0.1.1.dist-info/RECORD
