Metadata-Version: 2.4
Name: fancylogger_demo
Version: 0.1.1
Summary: Just a demo
Author-email: Kevin <allen920822@gamil.com>
Requires-Python: >=3.12
Requires-Dist: pandas>=2.2.3
